django_rethink/__init__.py
django_rethink/apimixins.py
django_rethink/apps.py
django_rethink/connection.py
django_rethink/serializers.py
django_rethink/tasks.py
django_rethink/tests.py
django_rethink/urls.py
django_rethink/views.py
django_rethink/management/__init__.py
django_rethink/management/commands/__init__.py
django_rethink/management/commands/syncrethinkdb.py
django_rethink-0.5.4.dist-info/LICENSE.txt
django_rethink-0.5.4.dist-info/METADATA
django_rethink-0.5.4.dist-info/WHEEL
django_rethink-0.5.4.dist-info/top_level.txt
django_rethink-0.5.4.dist-info/zip-safe
django_rethink-0.5.4.dist-info/RECORD
