Metadata-Version: 2.1
Name: django-rethink
Version: 0.5.4
Summary: Library to use RethinkDB with Django REST framework
Home-page: https://github.com/dhozac/django_rethink
Author: Klarna Bank AB
Author-email: daniel.zakrisson@klarna.com
License: Apache Software License
Platform: UNKNOWN
Classifier: Development Status :: 6 - Mature
Classifier: Environment :: Web Environment
Classifier: Framework :: Django :: 1.11
Classifier: Intended Audience :: System Administrators
Classifier: License :: OSI Approved :: Apache Software License
Requires-Dist: celery
Requires-Dist: djangorestframework (>3.4.0)
Requires-Dist: rethinkdb
Requires-Dist: deepdiff (>3.2.0)
